{
  "RxCUI": "1000089",
  "Name": "alcaftadine 2.5 MG/ML Ophthalmic Solution [Lastacaft]",
  "IsBrand": true,
  "Brand_Mate_RxCUI": "1000089",
  "Generic_Mate_RxCUI": "",
  "Ingredient_Name": "Alcaftadine Mgml",
  "Manufacturer_Name": "Lastacaft",
  "Strength": "2.5 MG/ML",
  "Form": "",
  "prices": {
    "00023429003": {
      "06/23/2021": 75.97867,
      "11/22/2017": 62.95375,
      "01/01/2018": 68.93436,
      "10/17/2018": 68.31867,
      "01/01/2019": 71.66697,
      "12/18/2019": 72.131,
      "06/17/2020": 71.54067,
      "10/21/2020": 72.07133,
      "01/01/2021": 75.6749
    },
    "00023429105": {
      "05/22/2024": 2.83695,
      "06/19/2024": 2.83858,
      "07/17/2024": 2.83177,
      "09/18/2024": 2.83891,
      "12/18/2024": 2.83821,
      "02/19/2025": 2.84123,
      "04/23/2025": 2.842,
      "08/20/2025": 2.84241,
      "09/17/2025": 2.83656,
      "10/22/2025": 2.83822,
      "11/19/2025": 2.83972
    }
  }
}