{
  "RxCUI": "1365660",
  "Name": "24 HR oxcarbazepine 150 MG Extended Release Oral Tablet [Oxtellar]",
  "IsBrand": true,
  "Brand_RxCUI": "1365660",
  "Generic_RxCUI": "1365653",
  "Ingredient_Name": "Hr Oxcarbazepine Extended Release",
  "Manufacturer_Name": "Oxtellar",
  "Strength": "24 HR",
  "Form": "",
  "prices": {
    "17772012101": {
      "06/29/2017": 5.50813,
      "01/01/2018": 5.94878,
      "01/01/2019": 6.42468,
      "01/01/2020": 6.93866,
      "01/01/2021": 7.35498,
      "04/21/2021": 7.2626,
      "01/01/2022": 7.69843,
      "01/01/2023": 8.16041,
      "01/01/2024": 8.65004,
      "05/22/2024": 8.63264,
      "06/19/2024": 8.65128,
      "07/17/2024": 8.62633,
      "08/21/2024": 8.65837,
      "09/18/2024": 8.65559,
      "10/23/2024": 8.65258,
      "11/20/2024": 8.65509,
      "12/18/2024": 8.65415,
      "02/19/2025": 8.65653,
      "03/19/2025": 8.66653,
      "04/01/2025": 9.18661
    }
  }
}