{
  "RxCUI": "1375954",
  "Name": "doxylamine succinate 10 MG / pyridoxine hydrochloride 10 MG Delayed Release Oral Tablet [Diclegis]",
  "IsBrand": true,
  "Brand_RxCUI": "1375954",
  "Generic_RxCUI": "1375948",
  "Ingredient_Name": "Doxylamine Succinate Pyridoxine Hydrochloride Delayed Release",
  "Manufacturer_Name": "Diclegis",
  "Strength": "10 MG",
  "Form": "",
  "prices": {
    "55494010010": {
      "07/01/2017": 6.03901,
      "08/23/2017": 5.99194,
      "01/01/2018": 6.53493,
      "10/17/2018": 6.55239,
      "05/22/2019": 6.59923,
      "03/18/2020": 6.56455,
      "06/15/2020": 5.20569,
      "08/19/2020": 5.36008,
      "09/23/2020": 5.24168,
      "02/17/2021": 5.19926,
      "11/17/2021": 5.18322,
      "3/23/2022": 5.2322,
      "2/22/2023": 5.19061,
      "12/20/2023": 5.22268,
      "04/01/2024": 3.12975,
      "08/21/2024": 3.12473,
      "09/18/2024": 3.12264,
      "10/23/2024": 3.12389,
      "11/20/2024": 3.12268,
      "12/18/2024": 3.12159,
      "01/01/2025": 2.48962,
      "05/21/2025": 2.49334,
      "06/18/2025": 2.49464,
      "07/01/2025": 1.99571,
      "11/19/2025": 1.99551
    }
  }
}