{
  "RxCUI": "238405",
  "Name": "zinc oxide 0.25 MG/MG Topical Ointment",
  "IsBrand": false,
  "Brand_RxCUI": "",
  "Generic_RxCUI": "238405",
  "Ingredient_Name": "Zinc Oxide Mgmg",
  "Manufacturer_Name": "",
  "Strength": "0.25 MG/MG",
  "Form": "Topical Ointment",
  "prices": {
    "70000048801": {
      "10/21/2020": 0.03993,
      "04/21/2021": 0.04014,
      "08/18/2021": 0.03979,
      "09/22/2021": 0.04002,
      "11/17/2021": 0.04,
      "12/18/2024": 0.03892,
      "01/22/2025": 0.03917,
      "02/19/2025": 0.03962,
      "03/19/2025": 0.03956,
      "04/23/2025": 0.03923,
      "05/21/2025": 0.03885,
      "06/18/2025": 0.03851,
      "07/23/2025": 0.03827,
      "08/20/2025": 0.03799,
      "09/17/2025": 0.03801,
      "10/22/2025": 0.03849,
      "11/19/2025": 0.03921
    }
  }
}