{
  "RxCUI": "2395775",
  "Name": "30 ACTUAT fluticasone furoate 0.2 MG/ACTUAT / umeclidinium 0.0625 MG/ACTUAT / vilanterol 0.025 MG/ACTUAT Dry Powder Inhaler [Trelegy]",
  "IsBrand": true,
  "Brand_RxCUI": "2395775",
  "Generic_RxCUI": "2395774",
  "Ingredient_Name": "Actuat Fluticasone Furoate Mgactuat Umeclidinium Mgactuat Vilanterol Mgactuat Dry Inhaler",
  "Manufacturer_Name": "Trelegy",
  "Strength": "30 ACTU",
  "Form": "Dry Powder Inhaler",
  "prices": {
    "00173089310": {
      "11/17/2021": 9.65663,
      "1/1/2022": 9.94643,
      "01/01/2023": 10.24482,
      "10/18/2023": 10.22537,
      "01/01/2024": 10.53223,
      "05/22/2024": 10.53486,
      "06/19/2024": 10.53192,
      "07/17/2024": 10.53556,
      "08/21/2024": 10.53555,
      "09/18/2024": 10.53282,
      "10/23/2024": 10.5324,
      "11/20/2024": 10.53059,
      "12/18/2024": 10.52994,
      "01/01/2025": 10.84584,
      "05/21/2025": 10.83313,
      "06/18/2025": 10.83183,
      "07/23/2025": 10.83388,
      "08/20/2025": 10.8332,
      "09/17/2025": 10.83388,
      "10/22/2025": 10.83576,
      "11/19/2025": 10.8359
    }
  }
}