{
  "RxCUI": "388517",
  "Name": "calcitriol 0.000003 MG/MG Topical Ointment",
  "IsBrand": false,
  "Brand_RxCUI": "883358",
  "Generic_RxCUI": "388517",
  "Ingredient_Name": "Calcitriol Mgmg",
  "Manufacturer_Name": "",
  "Strength": "0.000003 MG/MG",
  "Form": "Topical Ointment",
  "prices": {
    "45802060801": {
      "09/18/2024": 4.6995,
      "11/20/2024": 4.69943,
      "12/18/2024": 4.64965,
      "01/22/2025": 4.62472,
      "02/19/2025": 4.55002
    },
    "68308066510": {
      "09/18/2024": 4.6995,
      "11/20/2024": 4.69943,
      "12/18/2024": 4.64965,
      "01/22/2025": 4.62472,
      "02/19/2025": 4.55002
    }
  }
}