{
  "RxCUI": "1093073",
  "Name": "clomiphene citrate 50 MG Oral Tablet [Clomid]",
  "IsBrand": true,
  "Brand_Mate_RxCUI": "1093073",
  "Generic_Mate_RxCUI": "",
  "Ingredient_Name": "Clomiphene Citrate",
  "Manufacturer_Name": "Clomid",
  "Strength": "50 MG",
  "Form": "",
  "prices": {
    "00713088509": {
      "05/23/2023": 6.18475,
      "02/01/2024": 6.79887,
      "05/22/2024": 6.86256,
      "06/19/2024": 6.85948,
      "07/03/2024": 7.54451,
      "11/20/2024": 7.54007,
      "12/18/2024": 7.54773,
      "01/22/2025": 7.55863,
      "02/04/2025": 9.0595,
      "06/18/2025": 9.03423,
      "07/23/2025": 9.0242,
      "08/01/2025": 11.00656
    },
    "00713088530": {
      "05/23/2023": 6.18475,
      "02/01/2024": 6.79887,
      "05/22/2024": 6.86256,
      "06/19/2024": 6.85948,
      "07/03/2024": 7.54451,
      "11/20/2024": 7.54007,
      "12/18/2024": 7.54773,
      "01/22/2025": 7.55863,
      "02/04/2025": 9.0595,
      "06/18/2025": 9.03423,
      "07/23/2025": 9.0242,
      "08/01/2025": 11.00656
    }
  }
}